calc_pi-0.1.0.dist-info/METADATA
calc_pi-0.1.0.dist-info/WHEEL
calc_pi/__init__.py
calc_pi/calc_pi.cpython-313-x86_64-linux-gnu.so
calc_pi-0.1.0.dist-info/RECORD
