Metadata-Version: 2.4
Name: calc_pi
Version: 0.1.0
Summary: CLI for calculating millions of Pi digits within seconds. Various algorithms are supported.
Keywords: pi,cli,rust,benchmark,python
Author: BreezeWhite, <miyashita2010@tuta.io>
Author-email: BreezeWhite, <miyashita2010@tuta.io>
License: Apache-2.0
Project-URL: Source Code, https://github.com/BreezeWhite/calc_pi
